uup2sksearcher/__init__.py
uup2sksearcher/builder.py
uup2sksearcher/searcher.py
uup2sksearcher-0.0.4.dist-info/METADATA
uup2sksearcher-0.0.4.dist-info/WHEEL
uup2sksearcher-0.0.4.dist-info/top_level.txt
uup2sksearcher-0.0.4.dist-info/RECORD
